embedding_tool/__init__.py
embedding_tool/_nbdev.py
embedding_tool/core.py
embedding_tool-0.1.1.dist-info/LICENSE
embedding_tool-0.1.1.dist-info/METADATA
embedding_tool-0.1.1.dist-info/WHEEL
embedding_tool-0.1.1.dist-info/entry_points.txt
embedding_tool-0.1.1.dist-info/top_level.txt
embedding_tool-0.1.1.dist-info/RECORD
