Metadata-Version: 2.1
Name: embedding-tool
Version: 0.1.1
Summary: An embedding toolkit that can perform multiple embedding process which are low-dimensional embedding (dimension reduction), categorical variable embedding, and financial time-series embedding.
Home-page: https://github.com/thisisphume/embedding_tool/tree/master/
Author: Phume Ngampornsukswadi
Author-email: thisisphume@gmail.com
License: Apache Software License 2.0
Keywords: autoencoder PCA embedding
Platform: UNKNOWN
Classifier: Development Status :: 3 - Alpha
Classifier: Intended Audience :: Developers
Classifier: License :: OSI Approved :: Apache Software License
Classifier: Natural Language :: English
Classifier: Programming Language :: Python :: 3.6
Classifier: Programming Language :: Python :: 3.7
Classifier: Programming Language :: Python :: 3.8
Requires-Python: >=3.6
